README.txt
setup.cfg
setup.py
softwarefabrica/__init__.py
softwarefabrica.django.common.egg-info/PKG-INFO
softwarefabrica.django.common.egg-info/SOURCES.txt
softwarefabrica.django.common.egg-info/dependency_links.txt
softwarefabrica.django.common.egg-info/namespace_packages.txt
softwarefabrica.django.common.egg-info/not-zip-safe
softwarefabrica.django.common.egg-info/requires.txt
softwarefabrica.django.common.egg-info/top_level.txt
softwarefabrica/django/__init__.py
softwarefabrica/django/common/__init__.py
softwarefabrica/django/common/bzrcachedrev.py
softwarefabrica/django/common/finddata.py
softwarefabrica/django/common/managers.py
softwarefabrica/django/common/models.py
softwarefabrica/django/common/search.py
softwarefabrica/django/common/version.py
softwarefabrica/django/common/views.py