Metadata-Version: 1.0
Name: softwarefabrica.django.common
Version: 0.9dev-BZR-r33-panta-elasticworld.org-20091021152850-jlekcpgm5x5a9get
Summary: Common infrastructure for advanced SoftwareFabrica django projects
Home-page: http://cheeseshop.python.org/pypi/softwarefabrica.django.common/
Author: Marco Pantaleoni
Author-email: m.pantaleoni@softwarefabrica.org
License: GNU GPL v2
Download-URL: http://pypi.python.org/packages/source/s/softwarefabrica.django.common/softwarefabrica.django.common-0.9dev-BZR-r33-panta-elasticworld.org-20091021152850-jlekcpgm5x5a9get.tar.gz
Keywords: common infrastructure django softwarefabrica
Platform: UNKNOWN
Classifier: Development Status :: 4 - Beta
Classifier: Framework :: Django
Classifier: Intended Audience :: Developers
Classifier: License :: OSI Approved :: GNU General Public License (GPL)
Classifier: Operating System :: OS Independent
Classifier: Programming Language :: Python :: 2.3
Classifier: Topic :: Software Development :: Libraries :: Python Modules
